scikit_sampling-1.1.0.dist-info/licenses/LICENSE
sksampling/__init__.py
sksampling/estimation.py
scikit_sampling-1.1.0.dist-info/METADATA
scikit_sampling-1.1.0.dist-info/WHEEL
scikit_sampling-1.1.0.dist-info/top_level.txt
scikit_sampling-1.1.0.dist-info/RECORD
