Metadata-Version: 2.4
Name: scikit-sampling
Version: 1.1.0
Summary: A set of python modules for dataset sampling
Author-email: Leonardo Moraes <leomaurodesenv@users.noreply.github.com>
License-Expression: MIT
Project-URL: homepage, https://github.com/leomaurodesenv/scikit-sampling
Project-URL: source, https://github.com/leomaurodesenv/scikit-sampling
Project-URL: tracker, https://github.com/leomaurodesenv/scikit-sampling/issues
Classifier: Intended Audience :: Science/Research
Classifier: Intended Audience :: Developers
Classifier: Programming Language :: Python
Classifier: Topic :: Scientific/Engineering
Classifier: Development Status :: 4 - Beta
Classifier: Programming Language :: Python :: 3
Classifier: Programming Language :: Python :: 3.10
Classifier: Programming Language :: Python :: 3.11
Classifier: Programming Language :: Python :: 3.12
Classifier: Programming Language :: Python :: 3.13
Requires-Python: >=3.10
License-File: LICENSE
Requires-Dist: scipy<2,>=1.15.0
Provides-Extra: build
Requires-Dist: setuptools<90,>=80.9.0; extra == "build"
Requires-Dist: uv<0.8,>=0.7.12; extra == "build"
Requires-Dist: python-semantic-release~=10.0; extra == "build"
Dynamic: license-file
